cic/__init__.py
cic-0.1.0.dist-info/METADATA
cic-0.1.0.dist-info/WHEEL
cic-0.1.0.dist-info/top_level.txt
cic-0.1.0.dist-info/RECORD
